[
  {
    "line": 1,
    "elements": [
      {
        "start_timestamp": "2020-08-06T20:12:33.902Z",
        "line": 72,
        "name": "Verify if user is able to use search function in redfish search page",
        "description": "",
        "id": "validate-redfish-workflows--page;verify-if-user-is-able-to-use-search-function-in-redfish-search-page;;2",
        "type": "scenario",
        "keyword": "Scenario Outline",
        "steps": [
          {
            "result": {
              "duration": 9337000000,
              "status": "passed"
            },
            "line": 63,
            "name": "Initialize the browser with chrome",
            "match": {
              "location": "stepDefinations.StepDefination.initialize_the_browser_with_chrome()"
            },
            "keyword": "Given "
          },
          {
            "result": {
              "duration": 3192000000,
              "status": "passed"
            },
            "line": 64,
            "name": "Open Web Application \"redfishUrl\"",
            "match": {
              "arguments": [
                {
                  "val": "\"redfishUrl\"",
                  "offset": 21
                }
              ],
              "location": "stepDefinations.StepDefination.open_web_application(java.lang.String)"
            },
            "keyword": "And "
          },
          {
            "result": {
              "duration": 42785000000,
              "status": "passed"
            },
            "line": 65,
            "name": "User enters User Name \"99160101NM\" and Password \"Password1\"",
            "match": {
              "arguments": [
                {
                  "val": "\"99160101NM\"",
                  "offset": 22
                },
                {
                  "val": "\"Password1\"",
                  "offset": 48
                }
              ],
              "location": "stepDefinations.StepDefination.user_enters_user_name_and_password(java.lang.String,java.lang.String)"
            },
            "keyword": "When "
          },
          {
            "result": {
              "duration": 21000000,
              "status": "passed"
            },
            "line": 66,
            "name": "Verify if the web page title actual \"Home\"",
            "match": {
              "arguments": [
                {
                  "val": "\"Home\"",
                  "offset": 36
                }
              ],
              "location": "stepDefinations.StepDefination.Verify_if_the_web_page_title_actual(java.lang.String)"
            },
            "keyword": "Then "
          },
          {
            "result": {
              "duration": 3894000000,
              "status": "passed"
            },
            "line": 67,
            "name": "Verify search functionality with Child Name \"Javier Glawsop\" and Parent Name \"Carolyne Glawsop\"",
            "match": {
              "arguments": [
                {
                  "val": "\"Javier Glawsop\"",
                  "offset": 44
                },
                {
                  "val": "\"Carolyne Glawsop\"",
                  "offset": 77
                }
              ],
              "location": "stepDefinations.StepDefination.verify_search_functionality_with_child_name_and_parent_name(java.lang.String,java.lang.String)"
            },
            "keyword": "Then "
          },
          {
            "result": {
              "duration": 3014000000,
              "status": "passed"
            },
            "line": 68,
            "name": "Verify search functionality with Invalid Child Name \"@#$\" and Invalid Parent Name \"@#$\"",
            "match": {
              "arguments": [
                {
                  "val": "\"@#$\"",
                  "offset": 52
                },
                {
                  "val": "\"@#$\"",
                  "offset": 82
                }
              ],
              "location": "stepDefinations.StepDefination.verify_search_functionality_with_invalid_child_name_and_invalid_parent_name(java.lang.String,java.lang.String)"
            },
            "keyword": "Then "
          },
          {
            "result": {
              "duration": 11942000000,
              "status": "passed"
            },
            "line": 69,
            "name": "Logout from redfish and close browser",
            "match": {
              "location": "stepDefinations.StepDefination.Logout_from_redfish_and_close_browser()"
            },
            "keyword": "Then "
          }
        ],
        "tags": [
          {
            "name": "@RedfishSearchpage"
          },
          {
            "name": "@Regression"
          }
        ]
      }
    ],
    "name": "Validate Redfish Workflows  Page",
    "description": "",
    "id": "validate-redfish-workflows--page",
    "keyword": "Feature",
    "uri": "file:src/test/java/features/RedfishWorkflow.feature",
    "tags": []
  }
]